Metadata-Version: 2.1
Name: blacken-selection
Version: 0.2.0
Summary: Apply black formatter for a piece of python source code
Home-page: https://github.com/gibizer/blacken_selection
Author: Balazs Gibizer
Author-email: gibizer@gmail.com
License: Apache License 2.0
Platform: UNKNOWN
Requires-Python: >=3.6
